{
  "name": "forest_minimal",
  "dimension": "square",
  "background_type": "gradient",
  "color_scheme": "gradient_forest",
  "gradient_direction": "vertical",
  "pattern_type": null,
  "pattern_spacing": 50,
  "pattern_angle": 45,
  "add_vignette": false,
  "vignette_intensity": 0.6,
  "add_noise": true,
  "noise_intensity": 8,
  "add_blur_region": false,
  "logo_position": "top-right",
  "logo_size": [
    200,
    200
  ],
  "logo_margin": 40,
  "headline_font": "fonts/Poppins-Bold.ttf",
  "headline_size": 68,
  "headline_position": [
    40,
    420
  ],
  "headline_max_width": 900,
  "headline_shadow": false,
  "headline_outline": false,
  "has_subheadline": true,
  "subheadline_font": "fonts/Poppins-Regular.ttf",
  "subheadline_size": 40,
  "subheadline_position": [
    40,
    580
  ],
  "subheadline_max_width": 900,
  "use_text_box": false,
  "text_box_position": [
    40,
    700
  ],
  "text_box_size": [
    1000,
    200
  ],
  "text_box_bg_opacity": 180
}